flw/__init__.py
flw-0.0.0.dist-info/METADATA
flw-0.0.0.dist-info/WHEEL
flw-0.0.0.dist-info/top_level.txt
flw-0.0.0.dist-info/RECORD
