Metadata-Version: 2.1
Name: flw
Version: 0.0.0
Summary: ...
Home-page: https://www.google.com
Author: ...
License: MIT
